{"schemaVersion":"1.0.0","taxDomain":"PIT","asOf":"2026-07-19","scope":{"basis":"Base pit-rule-map sourceDiscovery inventory","entityCount":86,"description":"Planning map for every jurisdiction in the base source-discovery inventory. Planning families are not accepted tax-law classifications until source-indexed."},"dispositions":["ALREADY_IMPLEMENTED","DIRECT_CALCULATOR","PARENT_SYSTEM_DERIVATIVE","NO_PIT_VERIFICATION","NO_RESIDENT_POPULATION","RESTRICTED_OR_DISPUTED_SOURCE"],"sourcePlans":{"accepted-package":{"requiredEvidence":["accepted TaxCraft country package and implementation overlay"],"exitCriteria":"Remain synchronized with the accepted implementation record."},"sovereign-primary":{"requiredEvidence":["current tax authority or finance ministry rate material","controlling statute or official gazette","tax-year applicability confirmation"],"exitCriteria":"Promote to source-indexed only after family and maintained-year structure are supported by primary sources."},"parent-application":{"requiredEvidence":["parent-jurisdiction tax authority material","territorial application statute or official territorial guidance","local deviations and tax-year applicability"],"exitCriteria":"Determine whether to implement an alias, a parameter override, or an independent territorial package."},"no-pit-verification":{"requiredEvidence":["official statement or legislation confirming no ordinary PIT","confirmation of payroll, social, solidarity, or income-linked levies","effective-date confirmation"],"exitCriteria":"Implement NO_PIT only when ordinary PIT absence and exclusions are explicit."},"territorial-status":{"requiredEvidence":["official population or territorial-status source","applicable employment or expedition tax rules if any","parent-jurisdiction application rule"],"exitCriteria":"Mark no ordinary resident calculator only after confirming population and applicable tax scope."},"restricted-primary":{"requiredEvidence":["official gazette or legislation in the authoritative language","tax authority or finance ministry material where accessible","independent professional cross-check used only to locate and interpret primary law"],"exitCriteria":"Do not encode executable parameters until primary-law provenance and administering authority are clear."}},"summary":{"DIRECT_CALCULATOR":45,"RESTRICTED_OR_DISPUTED_SOURCE":10,"NO_PIT_VERIFICATION":8,"NO_RESIDENT_POPULATION":7,"PARENT_SYSTEM_DERIVATIVE":15,"ALREADY_IMPLEMENTED":1},"entries":{"AD":{"planningFamily":"PROGRESSIVE_RELIEFS","disposition":"DIRECT_CALCULATOR","sourcePlan":"sovereign-primary","priority":2},"AF":{"planningFamily":"MULTI_SCHEDULE","disposition":"RESTRICTED_OR_DISPUTED_SOURCE","sourcePlan":"restricted-primary","priority":4},"AG":{"planningFamily":"NO_PIT","disposition":"NO_PIT_VERIFICATION","sourcePlan":"no-pit-verification","priority":1},"AI":{"planningFamily":"NO_PIT","disposition":"NO_PIT_VERIFICATION","sourcePlan":"no-pit-verification","priority":1},"AQ":{"planningFamily":"NO_PIT","disposition":"NO_RESIDENT_POPULATION","sourcePlan":"territorial-status","priority":3,"notes":"No permanent resident population; retain ISO coverage without an ordinary citizen calculator unless an applicable employment regime is identified."},"AS":{"planningFamily":"COMPLEX_COMPOSITE","disposition":"PARENT_SYSTEM_DERIVATIVE","sourcePlan":"parent-application","priority":1,"parentJurisdiction":"US"},"AX":{"planningFamily":"MULTI_LAYER","disposition":"PARENT_SYSTEM_DERIVATIVE","sourcePlan":"parent-application","priority":1,"parentJurisdiction":"FI"},"BF":{"planningFamily":"PROGRESSIVE_RELIEFS","disposition":"DIRECT_CALCULATOR","sourcePlan":"sovereign-primary","priority":2},"BI":{"planningFamily":"PROGRESSIVE_RELIEFS","disposition":"DIRECT_CALCULATOR","sourcePlan":"sovereign-primary","priority":2},"BJ":{"planningFamily":"PROGRESSIVE_RELIEFS","disposition":"DIRECT_CALCULATOR","sourcePlan":"sovereign-primary","priority":2},"BL":{"planningFamily":"HOUSEHOLD_FILING","disposition":"PARENT_SYSTEM_DERIVATIVE","sourcePlan":"parent-application","priority":1,"parentJurisdiction":"FR"},"BT":{"planningFamily":"PROGRESSIVE_RELIEFS","disposition":"DIRECT_CALCULATOR","sourcePlan":"sovereign-primary","priority":2},"BV":{"planningFamily":"NO_PIT","disposition":"NO_RESIDENT_POPULATION","sourcePlan":"territorial-status","priority":3,"notes":"Uninhabited dependency; verify whether any tax rule applies to temporary personnel before exposing a calculator."},"BY":{"planningFamily":"FLAT_WITH_ALLOWANCE","disposition":"DIRECT_CALCULATOR","sourcePlan":"sovereign-primary","priority":2},"BZ":{"planningFamily":"PROGRESSIVE_RELIEFS","disposition":"DIRECT_CALCULATOR","sourcePlan":"sovereign-primary","priority":2},"CC":{"planningFamily":"SIMPLE_PROGRESSIVE","disposition":"PARENT_SYSTEM_DERIVATIVE","sourcePlan":"parent-application","priority":1,"parentJurisdiction":"AU"},"CF":{"planningFamily":"PROGRESSIVE_RELIEFS","disposition":"DIRECT_CALCULATOR","sourcePlan":"sovereign-primary","priority":2},"CK":{"planningFamily":"PROGRESSIVE_RELIEFS","disposition":"DIRECT_CALCULATOR","sourcePlan":"sovereign-primary","priority":2},"CU":{"planningFamily":"MULTI_SCHEDULE","disposition":"RESTRICTED_OR_DISPUTED_SOURCE","sourcePlan":"restricted-primary","priority":4},"CW":{"planningFamily":"PROGRESSIVE_RELIEFS","disposition":"DIRECT_CALCULATOR","sourcePlan":"sovereign-primary","priority":2},"CX":{"planningFamily":"SIMPLE_PROGRESSIVE","disposition":"PARENT_SYSTEM_DERIVATIVE","sourcePlan":"parent-application","priority":1,"parentJurisdiction":"AU"},"DJ":{"planningFamily":"PROGRESSIVE_RELIEFS","disposition":"DIRECT_CALCULATOR","sourcePlan":"sovereign-primary","priority":2},"DM":{"planningFamily":"PROGRESSIVE_RELIEFS","disposition":"DIRECT_CALCULATOR","sourcePlan":"sovereign-primary","priority":2},"EH":{"planningFamily":"COMPLEX_COMPOSITE","disposition":"RESTRICTED_OR_DISPUTED_SOURCE","sourcePlan":"restricted-primary","priority":4,"notes":"Disputed territorial administration requires administration-specific scoping before any executable model."},"ER":{"planningFamily":"PROGRESSIVE_RELIEFS","disposition":"RESTRICTED_OR_DISPUTED_SOURCE","sourcePlan":"restricted-primary","priority":4},"FK":{"planningFamily":"PROGRESSIVE_RELIEFS","disposition":"DIRECT_CALCULATOR","sourcePlan":"sovereign-primary","priority":2},"FM":{"planningFamily":"MULTI_SCHEDULE","disposition":"DIRECT_CALCULATOR","sourcePlan":"sovereign-primary","priority":2},"FO":{"planningFamily":"MULTI_LAYER","disposition":"DIRECT_CALCULATOR","sourcePlan":"sovereign-primary","priority":2},"GD":{"planningFamily":"PROGRESSIVE_RELIEFS","disposition":"DIRECT_CALCULATOR","sourcePlan":"sovereign-primary","priority":2},"GF":{"planningFamily":"HOUSEHOLD_FILING","disposition":"PARENT_SYSTEM_DERIVATIVE","sourcePlan":"parent-application","priority":1,"parentJurisdiction":"FR"},"GM":{"planningFamily":"PROGRESSIVE_RELIEFS","disposition":"DIRECT_CALCULATOR","sourcePlan":"sovereign-primary","priority":2},"GN":{"planningFamily":"PROGRESSIVE_RELIEFS","disposition":"DIRECT_CALCULATOR","sourcePlan":"sovereign-primary","priority":2},"GP":{"planningFamily":"HOUSEHOLD_FILING","disposition":"PARENT_SYSTEM_DERIVATIVE","sourcePlan":"parent-application","priority":1,"parentJurisdiction":"FR"},"GS":{"planningFamily":"NO_PIT","disposition":"NO_RESIDENT_POPULATION","sourcePlan":"territorial-status","priority":3},"GW":{"planningFamily":"PROGRESSIVE_RELIEFS","disposition":"DIRECT_CALCULATOR","sourcePlan":"sovereign-primary","priority":2},"HM":{"planningFamily":"NO_PIT","disposition":"NO_RESIDENT_POPULATION","sourcePlan":"territorial-status","priority":3},"HT":{"planningFamily":"PROGRESSIVE_RELIEFS","disposition":"DIRECT_CALCULATOR","sourcePlan":"sovereign-primary","priority":2},"IO":{"planningFamily":"NO_PIT","disposition":"NO_RESIDENT_POPULATION","sourcePlan":"territorial-status","priority":3,"notes":"No permanent civilian population; employment arrangements require separate scope verification."},"IR":{"planningFamily":"MULTI_SCHEDULE","disposition":"RESTRICTED_OR_DISPUTED_SOURCE","sourcePlan":"restricted-primary","priority":4},"KG":{"planningFamily":"FLAT_WITH_ALLOWANCE","disposition":"DIRECT_CALCULATOR","sourcePlan":"sovereign-primary","priority":2},"KI":{"planningFamily":"PROGRESSIVE_RELIEFS","disposition":"DIRECT_CALCULATOR","sourcePlan":"sovereign-primary","priority":2},"KM":{"planningFamily":"PROGRESSIVE_RELIEFS","disposition":"DIRECT_CALCULATOR","sourcePlan":"sovereign-primary","priority":2},"KN":{"planningFamily":"NO_PIT","disposition":"NO_PIT_VERIFICATION","sourcePlan":"no-pit-verification","priority":1},"KP":{"planningFamily":"COMPLEX_COMPOSITE","disposition":"RESTRICTED_OR_DISPUTED_SOURCE","sourcePlan":"restricted-primary","priority":4,"notes":"Primary legal material is difficult to verify; do not encode rates from unsourced summaries."},"MF":{"planningFamily":"HOUSEHOLD_FILING","disposition":"PARENT_SYSTEM_DERIVATIVE","sourcePlan":"parent-application","priority":1,"parentJurisdiction":"FR"},"MH":{"planningFamily":"MULTI_SCHEDULE","disposition":"DIRECT_CALCULATOR","sourcePlan":"sovereign-primary","priority":2},"ML":{"planningFamily":"PROGRESSIVE_RELIEFS","disposition":"DIRECT_CALCULATOR","sourcePlan":"sovereign-primary","priority":2},"MQ":{"planningFamily":"HOUSEHOLD_FILING","disposition":"PARENT_SYSTEM_DERIVATIVE","sourcePlan":"parent-application","priority":1,"parentJurisdiction":"FR"},"MS":{"planningFamily":"PROGRESSIVE_RELIEFS","disposition":"DIRECT_CALCULATOR","sourcePlan":"sovereign-primary","priority":2},"MW":{"planningFamily":"PROGRESSIVE_RELIEFS","disposition":"DIRECT_CALCULATOR","sourcePlan":"sovereign-primary","priority":2},"NE":{"planningFamily":"PROGRESSIVE_RELIEFS","disposition":"DIRECT_CALCULATOR","sourcePlan":"sovereign-primary","priority":2},"NF":{"planningFamily":"SIMPLE_PROGRESSIVE","disposition":"PARENT_SYSTEM_DERIVATIVE","sourcePlan":"parent-application","priority":1,"parentJurisdiction":"AU"},"NP":{"planningFamily":"PROGRESSIVE_RELIEFS","disposition":"DIRECT_CALCULATOR","sourcePlan":"sovereign-primary","priority":2},"NR":{"planningFamily":"MULTI_SCHEDULE","disposition":"DIRECT_CALCULATOR","sourcePlan":"sovereign-primary","priority":2},"NU":{"planningFamily":"PROGRESSIVE_RELIEFS","disposition":"DIRECT_CALCULATOR","sourcePlan":"sovereign-primary","priority":2},"PF":{"planningFamily":"MULTI_SCHEDULE","disposition":"DIRECT_CALCULATOR","sourcePlan":"sovereign-primary","priority":2,"notes":"French Polynesia has territory-specific income-linked levies; do not assume metropolitan French PIT."},"PM":{"planningFamily":"HOUSEHOLD_FILING","disposition":"PARENT_SYSTEM_DERIVATIVE","sourcePlan":"parent-application","priority":1,"parentJurisdiction":"FR"},"PN":{"planningFamily":"NO_PIT","disposition":"NO_PIT_VERIFICATION","sourcePlan":"no-pit-verification","priority":1,"notes":"Small resident population; verify local taxation and UK territorial arrangements before confirming NO_PIT."},"PW":{"planningFamily":"MULTI_SCHEDULE","disposition":"DIRECT_CALCULATOR","sourcePlan":"sovereign-primary","priority":2},"RE":{"planningFamily":"HOUSEHOLD_FILING","disposition":"PARENT_SYSTEM_DERIVATIVE","sourcePlan":"parent-application","priority":1,"parentJurisdiction":"FR"},"RU":{"planningFamily":"PROGRESSIVE_RELIEFS","disposition":"DIRECT_CALCULATOR","sourcePlan":"sovereign-primary","priority":2},"SB":{"planningFamily":"PROGRESSIVE_RELIEFS","disposition":"DIRECT_CALCULATOR","sourcePlan":"sovereign-primary","priority":2},"SC":{"planningFamily":"SIMPLE_PROGRESSIVE","disposition":"ALREADY_IMPLEMENTED","sourcePlan":"accepted-package","priority":0,"notes":"Promoted from the base discovery inventory by an accepted implementation overlay."},"SD":{"planningFamily":"PROGRESSIVE_RELIEFS","disposition":"RESTRICTED_OR_DISPUTED_SOURCE","sourcePlan":"restricted-primary","priority":4},"SH":{"planningFamily":"PROGRESSIVE_RELIEFS","disposition":"DIRECT_CALCULATOR","sourcePlan":"sovereign-primary","priority":2},"SJ":{"planningFamily":"MULTI_LAYER","disposition":"PARENT_SYSTEM_DERIVATIVE","sourcePlan":"parent-application","priority":1,"parentJurisdiction":"NO"},"SL":{"planningFamily":"PROGRESSIVE_RELIEFS","disposition":"DIRECT_CALCULATOR","sourcePlan":"sovereign-primary","priority":2},"SM":{"planningFamily":"PROGRESSIVE_RELIEFS","disposition":"DIRECT_CALCULATOR","sourcePlan":"sovereign-primary","priority":2},"SO":{"planningFamily":"PROGRESSIVE_RELIEFS","disposition":"RESTRICTED_OR_DISPUTED_SOURCE","sourcePlan":"restricted-primary","priority":4},"SY":{"planningFamily":"PROGRESSIVE_RELIEFS","disposition":"RESTRICTED_OR_DISPUTED_SOURCE","sourcePlan":"restricted-primary","priority":4},"TC":{"planningFamily":"NO_PIT","disposition":"NO_PIT_VERIFICATION","sourcePlan":"no-pit-verification","priority":1},"TF":{"planningFamily":"NO_PIT","disposition":"NO_RESIDENT_POPULATION","sourcePlan":"territorial-status","priority":3,"notes":"No permanent resident population; research-station arrangements are outside ordinary resident PIT scope."},"TG":{"planningFamily":"PROGRESSIVE_RELIEFS","disposition":"DIRECT_CALCULATOR","sourcePlan":"sovereign-primary","priority":2},"TJ":{"planningFamily":"FLAT_WITH_ALLOWANCE","disposition":"DIRECT_CALCULATOR","sourcePlan":"sovereign-primary","priority":2},"TK":{"planningFamily":"NO_PIT","disposition":"NO_PIT_VERIFICATION","sourcePlan":"no-pit-verification","priority":1},"TM":{"planningFamily":"FLAT_WITH_ALLOWANCE","disposition":"DIRECT_CALCULATOR","sourcePlan":"sovereign-primary","priority":2},"TO":{"planningFamily":"PROGRESSIVE_RELIEFS","disposition":"DIRECT_CALCULATOR","sourcePlan":"sovereign-primary","priority":2},"TV":{"planningFamily":"PROGRESSIVE_RELIEFS","disposition":"DIRECT_CALCULATOR","sourcePlan":"sovereign-primary","priority":2},"UM":{"planningFamily":"NO_PIT","disposition":"NO_RESIDENT_POPULATION","sourcePlan":"territorial-status","priority":3,"parentJurisdiction":"US","notes":"Uninhabited US outlying islands; no ordinary resident calculator is expected."},"VA":{"planningFamily":"NO_PIT","disposition":"NO_PIT_VERIFICATION","sourcePlan":"no-pit-verification","priority":1,"notes":"Verify employment and residence treatment separately from Italian PIT before confirming NO_PIT."},"VC":{"planningFamily":"PROGRESSIVE_RELIEFS","disposition":"DIRECT_CALCULATOR","sourcePlan":"sovereign-primary","priority":2},"VU":{"planningFamily":"NO_PIT","disposition":"NO_PIT_VERIFICATION","sourcePlan":"no-pit-verification","priority":1},"WF":{"planningFamily":"NO_PIT","disposition":"PARENT_SYSTEM_DERIVATIVE","sourcePlan":"parent-application","priority":1,"parentJurisdiction":"FR","notes":"Territory-specific position must be confirmed; do not inherit metropolitan French PIT automatically."},"WS":{"planningFamily":"PROGRESSIVE_RELIEFS","disposition":"DIRECT_CALCULATOR","sourcePlan":"sovereign-primary","priority":2},"YE":{"planningFamily":"PROGRESSIVE_RELIEFS","disposition":"RESTRICTED_OR_DISPUTED_SOURCE","sourcePlan":"restricted-primary","priority":4},"YT":{"planningFamily":"HOUSEHOLD_FILING","disposition":"PARENT_SYSTEM_DERIVATIVE","sourcePlan":"parent-application","priority":1,"parentJurisdiction":"FR"}}}
